odoo9_addon_event_registration_mass_mailing-9.0.1.0.0-py2.7-nspkg.pth
odoo_addons/event_registration_mass_mailing/__openerp__.py
odoo_addons/event_registration_mass_mailing/__init__.py
odoo_addons/event_registration_mass_mailing/README.rst
odoo_addons/event_registration_mass_mailing/models/email_template.py
odoo_addons/event_registration_mass_mailing/models/event_registration.py
odoo_addons/event_registration_mass_mailing/models/mass_mailing.py
odoo_addons/event_registration_mass_mailing/models/__init__.py
odoo_addons/event_registration_mass_mailing/i18n/es.po
odoo_addons/event_registration_mass_mailing/wizard/event_registration_mail_list_wizard.xml
odoo_addons/event_registration_mass_mailing/wizard/__init__.py
odoo_addons/event_registration_mass_mailing/wizard/event_registration_mail_list_wizard.py
odoo_addons/event_registration_mass_mailing/views/event_registration.xml
odoo_addons/event_registration_mass_mailing/tests/test_event_registration_mail_list_wizard.py
odoo_addons/event_registration_mass_mailing/tests/__init__.py
odoo_addons/event_registration_mass_mailing/tests/test_email_template.py
odoo9_addon_event_registration_mass_mailing-9.0.1.0.0.dist-info/top_level.txt
odoo9_addon_event_registration_mass_mailing-9.0.1.0.0.dist-info/WHEEL
odoo9_addon_event_registration_mass_mailing-9.0.1.0.0.dist-info/RECORD
odoo9_addon_event_registration_mass_mailing-9.0.1.0.0.dist-info/metadata.json
odoo9_addon_event_registration_mass_mailing-9.0.1.0.0.dist-info/DESCRIPTION.rst
odoo9_addon_event_registration_mass_mailing-9.0.1.0.0.dist-info/METADATA
odoo9_addon_event_registration_mass_mailing-9.0.1.0.0.dist-info/namespace_packages.txt
